[
  {
    "pageTitle": "Safe Data Room - Key Insights into the Safe Ecosystem",
    "description": "Uncover the impact of the Safe ecosystem in crypto. Explore detailed metrics on USDC storage, CryptoPunks holdings, and transaction volumes. Access comprehensive reports from Dune Analytics, Messari, Nansen, and more.",
    "image": "/images/DataRoom/meta-image-dataroom.jpg",
    "component": "common/MetaTags"
  },
  {
    "component": "DataRoom/Hero",
    "title": "Welcome to <b><em>Safe</em></b> Data Room",
    "text": "Explore live tracking of key metrics associated with <em>Safe</em> adoption"
  },
  {
    "component": "DataRoom/WorldGDP",
    "title": "<b><em>Safe</em> TVP</b> is",
    "text": "Total Volume Processed in <em>Safe</em> Smart Accounts can already be seen in comparison to World GDP.",
    "link": {
      "title": "Dune dashboard",
      "href": "https://dune.com/safe/all"
    }
  },
  {
    "component": "DataRoom/USDCStorage",
    "title": "<b><em>Safe</em></b> accounts store...<br/>",
    "text": "<b>of all USDC</b>",
    "link": {
      "title": "Dune",
      "href": "https://dune.com/queries/3867647"
    },
    "image": {
      "src": "/images/Dataroom/USDC.png",
      "alt": "USDC Coin"
    }
  },
  {
    "component": "DataRoom/CryptoPunks",
    "title": "Cryptopunks currently owned in <em>Safe</em>",
    "text": "Cryptopunks are vaulted up by their owners behind <em>Safe</em>’s multisig security",
    "link": {
      "title": "Dune dashboard",
      "href": "https://dune.com/safe/ethereum-nfts"
    }
  },
  {
    "component": "DataRoom/VolumeTransferred",
    "title": "Total Volume Processed via <b><em>Safe</em></b>",
    "link": {
      "title": "Dune dashboard",
      "href": "https://dune.com/safe/all"
    }
  },
  {
    "component": "DataRoom/FeesEarned",
    "title": "Annualized community aligned</br><b>fees earned</b>:",
    "fees": [
      {
        "label": "Native Swaps"
      },
      {
        "label": "Native Staking"
      },
      {
        "label": "Future Fees",
        "isLocked": true
      }
    ]
  },
  {
    "component": "DataRoom/TransactionsOnChain",
    "text": "<b>onchain transactions</b> originate from a <b>Safe Account</b>",
    "link": {
      "title": "Dune",
      "href": "https://dune.com/queries/3737066"
    }
  },
  {
    "component": "DataRoom/IndustryComparison",
    "title": "How <em>Safe</em> compares<br/>to others"
  },
  {
    "component": "DataRoom/AssetsSecured",
    "caption": "CEX vs Safe",
    "cexes": [
      {
        "name": "Robinhood CEX",
        "tvl": 17012090928.34492
      },
      {
        "name": "OKX",
        "tvl": 24070217201.141243
      },
      {
        "name": "Safe",
        "tvl": 71441479840.45575,
        "boxColor": "main"
      },
      {
        "name": "Binance",
        "tvl": 138294085853.49887
      }
    ],
    "title": "<em>Safe</em> TVL compares and surpasses major CEXs"
  },
  {
    "component": "DataRoom/CategoryLeaders",
    "leaders": [
      {
        "name": "Lido (Liquid Staking)",
        "tvl": 23090840136.379456
      },
      {
        "name": "Uniswap (Liquidity Pool)",
        "tvl": 4473126543.502114
      },
      {
        "name": "Safe",
        "tvl": 71441479840.45575,
        "boxColor": "main"
      },
      {
        "name": "EigenLayer (Re-Staking)",
        "tvl": 10710215713.14545
      },
      {
        "name": "AAVE",
        "tvl": 19023309395.7664
      }
    ],
    "title": "<b>Safe </b>TVL<br/><b>x</b><br/>TVL of <b>category leaders</b>"
  },
  {
    "component": "DataRoom/SeeMore",
    "text": "Want to see <b>more</b>?"
  },
  {
    "component": "DataRoom/ExternalLinksGrid",
    "title": "Dune Boards",
    "items": [
      {
        "title": "Safe on all chains",
        "image": {
          "src": "/images/dune-icon-name-logo.png",
          "alt": "Dune Analytics logo"
        },
        "link": {
          "href": "https://dune.com/safe/all"
        }
      },
      {
        "title": "Smart Account landscape",
        "image": {
          "src": "/images/dune-icon-name-logo.png",
          "alt": "Dune Analytics logo"
        },
        "link": {
          "href": "https://dune.com/safe/smart-accounts"
        }
      }
    ]
  },
  {
    "component": "DataRoom/ExternalLinksGrid",
    "title": "External Reports",
    "items": [
      {
        "title": "Messari Q3 2024",
        "image": {
          "src": "/images/messari-logo.svg",
          "alt": "Messari logo"
        },
        "link": {
          "href": "https://messari.io/report/state-of-safe-q3-2024"
        }
      },
      {
        "title": "Messari Q2 2024",
        "image": {
          "src": "/images/messari-logo.svg",
          "alt": "Messari logo"
        },
        "link": {
          "href": "https://messari.io/report/state-of-safe-q2-2024"
        }
      },
      {
        "title": "Messari Q1 2024",
        "image": {
          "src": "/images/messari-logo.svg",
          "alt": "Messari logo"
        },
        "link": {
          "href": "https://messari.io/report/state-of-safe-q1-2024"
        }
      },
      {
        "title": "Messari Q4 2023",
        "image": {
          "src": "/images/messari-logo.svg",
          "alt": "Messari logo"
        },
        "link": {
          "href": "https://messari.io/report/safe-q3-2023-brief"
        }
      },
      {
        "title": "Nansen Report",
        "image": {
          "src": "/images/nansen-logo.png",
          "alt": "Nansen logo"
        },
        "link": {
          "href": "https://research.nansen.ai/articles/account-abstraction-update-safe-core-setting-the-standard"
        }
      },
      {
        "title": "Greenfield One Thesis Post",
        "image": {
          "src": "/images/green-field-logo.svg",
          "alt": "Greenfield logo"
        },
        "link": {
          "href": "https://greenfield.xyz/wp-content/uploads/2024/04/2404_23_Report_on_Safe_final.pdf"
        }
      },
      {
        "title": "1kx Thesis Post",
        "image": {
          "src": "/images/1kx-logo.svg",
          "alt": "1kx logo"
        },
        "link": {
          "href": "https://medium.com/1kxnetwork/safe-unlocking-the-era-of-programmable-ownership-5a21214f4836"
        }
      }
    ]
  }
]
